[
  {
    "id": 6,
    "company": "Viaplay Group",
    "title": "Software Engineer",
    "companyWebSite": "https://viaplay.com",
    "timeRange": "06-2024 -> 09-2025",
    "showOnCv": true,
    "showOnWeb": true,
    "shortDescription": "Typescript Backend Developer creating high-quality platforms",
    "itemsDescriptions": [
      {
        "description": "Developed scalable serverless architectures on AWS Lambda, optimizing for efficiency and performance."
      },
      {
        "description": "Designed and maintained secure microservices in TypeScript and Node.js for reliable payment processing."
      },
      {
        "description": "Led cross-functional collaboration with product, design, and analytics teams to improve user activation flows."
      },
      {
        "description": "Automated deployments using Infrastructure as Code (IaC) to streamline release processes and enhance reliability."
      },
      {
        "description": "Ensured security and compliance with industry standards like PCI DSS for safeguarding payment data."
      }
    ],
    "usedSkills": [
      {
        "name": "TypeScript"
      },
      {
        "name": "Node.js"
      },
      {
        "name": "Lambda"
      },
      {
        "name": "AWS"
      }
    ]
  },
  {
    "id": 5,
    "company": "InnoIT Consulting",
    "title": "SSr Backend Developer",
    "companyWebSite": "https://www.linkedin.com/company/innoit-consulting/",
    "timeRange": "02-2022 -> 06-2024",
    "showOnCv": true,
    "showOnWeb": true,
    "shortDescription": "Typescript Backend Developer creating high-quality platforms",
    "itemsDescriptions": [
      {
        "description": "Led the development of a serverless AWS-based configurator process using TypeScript and KV database."
      },
      {
        "description": "Contributed to global product recommendations, reducing costs and enhancing scalability"
      }
    ],
    "usedSkills": [
      {
        "name": "TypeScript"
      },
      {
        "name": "Microservices"
      },
      {
        "name": "Microsoft Azure"
      },
      {
        "name": "Microsoft Bot Framework"
      }
    ]
  },
  {
    "id": 4,
    "company": "Settle Network",
    "title": "SSr Backend Developer",
    "companyWebSite": "https://www.settlenetwork.com/",
    "timeRange": "02-2022 -> 03-2023",
    "showOnCv": true,
    "showOnWeb": true,
    "shortDescription": "Member of the backend team of a fintech and crypto project",
    "itemsDescriptions": [
      {
        "description": "Worked on a new project to create a fiat and crypto wallet, using JavaScript and TypeScript."
      },
      {
        "description": "Achieved goals of reducing infrastructure costs and learning about new crypto technologies in a startup environment."
      }
    ],
    "usedSkills": [
      {
        "name": "JavaScript"
      },
      {
        "name": "Microservices"
      },
      {
        "name": "Crypto currencies"
      }
    ]
  },
  {
    "id": 3,
    "company": "Mercado Libre",
    "title": "Software Engineer Analyst",
    "companyWebSite": "https://mercadolibre.com/",
    "timeRange": "05-2021 -> 02-2022",
    "showOnCv": true,
    "showOnWeb": true,
    "shortDescription": "Part of the CX-IT team",
    "itemsDescriptions": [
      {
        "description": "Maintained CRM channels, including phone and messaging services, built with Java."
      },
      {
        "description": "Replaced a legacy monolith chat application with a microservices structure, primarily using Go."
      }
    ],
    "usedSkills": [
      {
        "name": "GoLang"
      },
      {
        "name": "Java"
      },
      {
        "name": "Microservices"
      },
      {
        "name": "Hexagonal Architecture"
      }
    ]
  },
  {
    "id": 2,
    "company": "Henry",
    "title": "Teaching Assistant",
    "companyWebSite": "https://www.soyhenry.com/",
    "timeRange": "05-2021 -> 07-2021",
    "showOnCv": false,
    "showOnWeb": true,
    "shortDescription": "Part-time",
    "itemsDescriptions": [
      {
        "description": "Supporting a designated group of students undertaking teacher designated activities"
      },
      {
        "description": "Promote their own continuous professional development, and engage enthusiastically with the processes of become a developer."
      }
    ],
    "usedSkills": [
      {
        "name": "JavaScript"
      },
      {
        "name": "TypeScript"
      },
      {
        "name": "React"
      },
      {
        "name": "Node"
      }
    ]
  },
  {
    "id": 1,
    "company": "Previous Experience",
    "title": "Aeronautical Engineer",
    "companyWebSite": "",
    "timeRange": "2012 -> 2020",
    "showOnCv": true,
    "showOnWeb": true,
    "shortDescription": "Full-time",
    "itemsDescriptions": [
      {
        "description": "working in main players of industries like Siemens and Airbus"
      },
      {
        "description": "Leading multidisciplinary team on differents sites"
      },
      {
        "description": "Negotiations with customers and contractors"
      }
    ],
    "usedSkills": [
      {
        "name": "multicultural working environment"
      },
      {
        "name": "Project Management"
      },
      {
        "name": "Leadership"
      }
    ]
  }
]
